aioeufyclean/__init__.py
aioeufyclean/connection.py
aioeufyclean/const.py
aioeufyclean/countries.py
aioeufyclean/device.py
aioeufyclean/discovery.py
aioeufyclean/eufy_cloud.py
aioeufyclean/exceptions.py
aioeufyclean/metadata.py
aioeufyclean/py.typed
aioeufyclean/tuya_cloud.py
aioeufyclean-0.5.1.dist-info/METADATA
aioeufyclean-0.5.1.dist-info/WHEEL
aioeufyclean-0.5.1.dist-info/top_level.txt
aioeufyclean-0.5.1.dist-info/RECORD
